{
    "chapters": [
        {
            "content": "localData/TitlePdf/Lecture4-descriptions.html",
            "pages": [
                {
                    "content": "https://apps.tlt.stonybrook.edu/vq/users/evannieuwenh/79/",
                    "duration": 107,
                    "title": "Veritasium - 4 Revolutionary Riddles Resolved!",
                    "type": "video"
                },
                {
                    "content": "https://apps.tlt.stonybrook.edu/vq/users/evannieuwenh/80/",
                    "duration": 458,
                    "title": "Integrating Electric Field",
                    "type": "video"
                },
                {
                    "content": "https://apps.tlt.stonybrook.edu/vq/users/evannieuwenh/81/",
                    "duration": 965,
                    "title": "More dQ - Spherical Coordinates",
                    "type": "video"
                },
                {
                    "content": "https://apps.tlt.stonybrook.edu/vq/users/evannieuwenh/82/",
                    "duration": 660,
                    "title": "Using Coordinates to Integrate in 3D",
                    "type": "video"
                },
                {
                    "content": "https://apps.tlt.stonybrook.edu/vq/users/evannieuwenh/83/",
                    "duration": 875,
                    "title": "Integrating Electric Field - Hollow Disk",
                    "type": "video"
                }
            ],
            "title": "PHY132 - Week 2",
            "type": "customCover"
        },
        {
            "content": "localData/TitlePdf/Lecture5-descriptions.html",
            "pages": [
                {
                    "content": "https://apps.tlt.stonybrook.edu/vq/users/evannieuwenh/84/",
                    "duration": 78,
                    "title": "Physics Girl - Physics of Skateboarding",
                    "type": "video"
                },
                {
                    "content": "https://apps.tlt.stonybrook.edu/vq/users/evannieuwenh/85/",
                    "duration": 173,
                    "title": "Possible Electric Field Integrals",
                    "type": "video"
                },
                {
                    "content": "https://apps.tlt.stonybrook.edu/vq/users/evannieuwenh/86/",
                    "duration": 397,
                    "title": "Hollow Disk (part a)",
                    "type": "video"
                },
                {
                    "content": "https://apps.tlt.stonybrook.edu/vq/users/evannieuwenh/87/",
                    "duration": 404,
                    "title": "Hollow Disk (part b)",
                    "type": "video"
                },
                {
                    "content": "https://apps.tlt.stonybrook.edu/vq/users/evannieuwenh/88/",
                    "duration": 932,
                    "title": "Hollow Disk (part c)",
                    "type": "video"
                },
                {
                    "content": "https://apps.tlt.stonybrook.edu/vq/users/evannieuwenh/89/",
                    "duration": 773,
                    "title": "Hollow Disk (part d)",
                    "type": "video"
                },
                {
                    "content": "https://apps.tlt.stonybrook.edu/vq/evannieuwenh/90/",
                    "duration": 273,
                    "title": "Ring of Charge (part a)",
                    "type": "video"
                }
            ],
            "title": "PHY132 - Week 2",
            "type": "customCover"
        },
        {
            "content": "localData/TitlePdf/Lecture6-descriptions.html",
            "pages": [
                {
                    "content": "https://apps.tlt.stonybrook.edu/vq/users/evannieuwenh/91/",
                    "duration": 107,
                    "title": "Smarter Every Day - The Walking Water Mystery",
                    "type": "video"
                },
                {
                    "content": "https://apps.tlt.stonybrook.edu/vq/users/evannieuwenh/92/",
                    "duration": 512,
                    "title": "Ring of Charge (part b)",
                    "type": "video"
                },
                {
                    "content": "https://apps.tlt.stonybrook.edu/vq/users/evannieuwenh/93/",
                    "duration": 287,
                    "title": "Ring of Charge (part c)",
                    "type": "video"
                },
                {
                    "content": "https://apps.tlt.stonybrook.edu/vq/users/evannieuwenh/94/",
                    "duration": 416,
                    "title": "Ring of Charge (part d)",
                    "type": "video"
                },
                {
                    "content": "https://apps.tlt.stonybrook.edu/vq/users/evannieuwenh/95/",
                    "duration": 254,
                    "title": "Ring of Charge (part e)",
                    "type": "video"
                },
                {
                    "content": "https://apps.tlt.stonybrook.edu/vq/users/evannieuwenh/96/",
                    "duration": 181,
                    "title": "Summary - Finite Line of Charge",
                    "type": "video"
                },
                {
                    "content": "https://apps.tlt.stonybrook.edu/vq/users/evannieuwenh/97/",
                    "duration": 55,
                    "title": "Summary - Full Ring of Charge",
                    "type": "video"
                },
                {
                    "content": "https://apps.tlt.stonybrook.edu/vq/users/evannieuwenh/98/",
                    "duration": 526,
                    "title": "Summary - Partial Ring of Charge",
                    "type": "video"
                },
                {
                    "content": "https://apps.tlt.stonybrook.edu/vq/users/evannieuwenh/99/",
                    "duration": 95,
                    "title": "Summary - Hollow Disk of Charge",
                    "type": "video"
                },
                {
                    "content": "https://apps.tlt.stonybrook.edu/vq/users/evannieuwenh/100/",
                    "duration": 405,
                    "title": "Summary - Partial Spherical Shell of Charge",
                    "type": "video"
                },
                {
                    "content": "https://apps.tlt.stonybrook.edu/vq/users/evannieuwenh/101/",
                    "duration": 110,
                    "title": "Sneak Peek - Gauss's Law",
                    "type": "video"
                }
            ],
            "title": "PHY132 - Week 2",
            "type": "customCover"
        }
    ],
    "localStorageKey": "PHY132",
    "overlayURLs": {}
}